{
  "parent": "quest_giver:root",
  "reputation": 10,
  "icon": "minecraft:white_wool",
  "start": {
    "title": {
      "text": "Unlock Loom"
    },
    "description": {
      "text": "No problem friend. Give me 15 emeralds and I'll teach you how to use the loom!"
    }
  },
  "complete": {
    "title": {
      "text": "Thanks!"
    },
    "description": {
      "text": "There you go!"
    }
  },
  "tasks": [
    {
      "item": {
        "item": "minecraft:emerald"
      },
      "id": "quest_giver:gift",
      "times": 15
    }
  ],
  "rewards": [
    {
      "command": "/pmmo admin @p add agility level 1",
      "id": "quest_giver:command"
    }
  ]
}