{
  "parent": "quest_giver:quest_0014_05",
  "reputation": 10,
  "icon": "minecraft:iron_sword",
  "start": {
    "title": {
      "text": "寻眼之路"
    },
    "description": {
      "text": "嗯……九尾不是一个普通的人类。不过没关系，当你见到他的时候就会明白了。"
    }
  },
  "complete": {
    "title": {
      "text": "寻眼之路"
    },
    "description": {
      "text": "嗯…到这个地步，我甚至都不感到惊讶了。干的漂亮。九尾是一个恶名昭著的凶灵……我不知道它为什么决定金盆洗手藏在一座废弃的谷仓。不管怎样，这是下一个眼睛守护者的行踪。万分小心，这次与你之前所面对的完全不同。"
    }
  },
  "tasks": [
    {
      "item": {
        "item": "endrem:exotic_eye"
      },
      "id": "quest_giver:item_pickup",
      "times": 1
    }
  ],
  "rewards": [
    {
      "command": "/dc addWaypoint @p custom:floating_island \"主线任务 - 浮空岛\"",
      "id": "quest_giver:command"
    },
    {
      "command": "/loot give @p loot minecraft:guildmaster4",
      "id": "quest_giver:command"
    },
    {
      "command": "/pmmo admin @p add magic level 1",
      "id": "quest_giver:command"
    },
    {
      "command": "/pmmo admin @p add smithing level 1",
      "id": "quest_giver:command"
    },
    {
      "command": "/advancement grant @p only simple_mobs:nine_tails_quest_complete",
      "id": "quest_giver:command"
    },
    {
      "command": "/gamestage add @p guildmaster6 true",
      "id": "quest_giver:command"
    }
  ]
}