{
  "parent": "quest_giver:root",
  "reputation": 10,
  "icon": "minecraft:stone",
  "start": {
    "title": {
      "text": "So?"
    },
    "description": {
      "text": "What do you say? 10 Emeralds to learn how to use the stonecutter."
    }
  },
  "complete": {
    "title": {
      "text": "Thanks!"
    },
    "description": {
      "text": "There you go!"
    }
  },
  "tasks": [
    {
      "item": {
        "item": "minecraft:emerald"
      },
      "id": "quest_giver:gift",
      "times": 10
    }
  ],
  "rewards": [
    {
      "command": "/pmmo admin @p add woodcutting level 1",
      "id": "quest_giver:command"
    },
    {
      "command": "/gamestage add @p StoneCutter",
      "id": "quest_giver:command"
    }
  ]
}